cloud_guardrails/__init__.py
cloud_guardrails/bin/__init__.py
cloud_guardrails/bin/cli.py
cloud_guardrails/bin/version.py
cloud_guardrails/command/__init__.py
cloud_guardrails/command/create_config_file.py
cloud_guardrails/command/create_parameters_file.py
cloud_guardrails/command/describe_policy.py
cloud_guardrails/command/generate_terraform.py
cloud_guardrails/command/list_policies.py
cloud_guardrails/command/list_services.py
cloud_guardrails/iam_definition/__init__.py
cloud_guardrails/iam_definition/azure_policies.py
cloud_guardrails/iam_definition/parameter.py
cloud_guardrails/iam_definition/policy_definition.py
cloud_guardrails/iam_definition/properties.py
cloud_guardrails/scrapers/__init__.py
cloud_guardrails/scrapers/azure_docs.py
cloud_guardrails/scrapers/compliance_data.py
cloud_guardrails/scrapers/parse_builtin_definitions.py
cloud_guardrails/scrapers/standard.py
cloud_guardrails/shared/__init__.py
cloud_guardrails/shared/config.py
cloud_guardrails/shared/parameters_categorized.py
cloud_guardrails/shared/utils.py
cloud_guardrails/shared/validate.py
cloud_guardrails/shared/data/azure_security_benchmark.html
cloud_guardrails/shared/data/ccmc-l3.html
cloud_guardrails/shared/data/cis_benchmark.html
cloud_guardrails/shared/data/compliance-data.csv
cloud_guardrails/shared/data/compliance-data.json
cloud_guardrails/shared/data/hipaa-hitrust-9-2.html
cloud_guardrails/shared/data/iam-definition.json
cloud_guardrails/shared/data/iso-27007.html
cloud_guardrails/shared/data/new-zealand-ism.html
cloud_guardrails/shared/data/nist-sp-800-171-r2.html
cloud_guardrails/shared/data/nist-sp-800-53-r4.html
cloud_guardrails/templates/__init__.py
cloud_guardrails/templates/config-template.yml.j2
cloud_guardrails/templates/config_template.py
cloud_guardrails/templates/parameters-template.yml.j2
cloud_guardrails/templates/parameters_template.py
cloud_guardrails/terraform/__init__.py
cloud_guardrails/terraform/guardrails.py
cloud_guardrails/terraform/terraform_no_params.py
cloud_guardrails-0.2.6.dist-info/LICENSE
cloud_guardrails-0.2.6.dist-info/METADATA
cloud_guardrails-0.2.6.dist-info/WHEEL
cloud_guardrails-0.2.6.dist-info/entry_points.txt
cloud_guardrails-0.2.6.dist-info/top_level.txt
cloud_guardrails-0.2.6.dist-info/zip-safe
cloud_guardrails-0.2.6.dist-info/RECORD
