Metadata-Version: 2.1
Name: cloud-guardrails
Version: 0.2.6
Summary: UNKNOWN
Home-page: https://github.com/salesforce/cloud-guardrails
Author: Kinnaird McQuade
Author-email: kinnairdm@gmail.com
License: UNKNOWN
Keywords: azure security
Platform: UNKNOWN
Classifier: Programming Language :: Python :: 3
Classifier: License :: OSI Approved :: MIT License
Classifier: Operating System :: OS Independent
Requires-Python: >=3.7
Requires-Dist: click
Requires-Dist: click-option-group
Requires-Dist: pyyaml
Requires-Dist: jinja2
Requires-Dist: tabulate
Requires-Dist: colorama
Requires-Dist: ruamel.yaml
Requires-Dist: beautifulsoup4
Requires-Dist: requests
